medmetric/__init__.py
medmetric/_version.py
medmetric/extractors/__init__.py
medmetric/extractors/medicalnet.py
medmetric/hub/__init__.py
medmetric/hub/medicalnet.py
medmetric/metrics/__init__.py
medmetric/metrics/fid.py
medmetric/metrics/mmd.py
medmetric/metrics/msssim.py
medmetric/models/__init__.py
medmetric/models/resnet.py
medmetric/utils/tensors.py
medmetric/weights/__init__.py
medmetric/weights/medicalnet.yaml
medmetric-0.1.1.dist-info/licenses/LICENSE
medmetric-0.1.1.dist-info/METADATA
medmetric-0.1.1.dist-info/WHEEL
medmetric-0.1.1.dist-info/top_level.txt
medmetric-0.1.1.dist-info/RECORD
