Metadata-Version: 2.4
Name: medmetric
Version: 0.1.1
Summary: Medical image synthesis metrics (FID/MMD/MS-SSIM) with MedicalNet feature extractor.
Author: Muhammad Nabi Yasinzai
License: MIT
Requires-Python: >=3.10
License-File: LICENSE
Requires-Dist: torch>=2.1.0
Requires-Dist: huggingface-hub>=0.20.1
Requires-Dist: pyyaml>=6.0.1
Provides-Extra: monai
Requires-Dist: monai>=1.3; extra == "monai"
Requires-Dist: scipy>=1.13; extra == "monai"
Provides-Extra: dev
Requires-Dist: pytest>=8; extra == "dev"
Dynamic: license-file
